python/__init__.py
python/__main__.py
python/dnsscanner_tui.py
python/iran-ipv4.cidrs
python/requirements.txt
python/slipstream-client/slipstream-client-all-platforms.tar.gz
python/slipstream-client/slipstream-client-all-platforms.zip
python/slipstream-client/linux/slipstream-client-linux-amd64
python/slipstream-client/mac/slipstream-client-darwin-amd64
python/slipstream-client/mac/slipstream-client-darwin-arm64
python/slipstream-client/windows/libcrypto-3-x64.dll
python/slipstream-client/windows/libssl-3-x64.dll
python/slipstream-client/windows/slipstream-client-windows-amd64.exe
pydns_scanner-1.2.3.data/data/python/iran-ipv4.cidrs
pydns_scanner-1.2.3.dist-info/METADATA
pydns_scanner-1.2.3.dist-info/WHEEL
pydns_scanner-1.2.3.dist-info/entry_points.txt
pydns_scanner-1.2.3.dist-info/licenses/LICENSE
pydns_scanner-1.2.3.dist-info/RECORD
