Metadata-Version: 2.4
Name: pydns-scanner
Version: 1.2.3
Summary: A high-performance DNS scanner with beautiful GitHub dark-themed TUI, parallel Slipstream proxy testing (5 concurrent), proxy authentication, and Iran CIDR bundle
Project-URL: Homepage, https://github.com/xullexer/PYDNS-Scanner
Project-URL: Repository, https://github.com/xullexer/PYDNS-Scanner
Project-URL: Issues, https://github.com/xullexer/PYDNS-Scanner/issues
Author: xullexer
License-Expression: MIT
License-File: LICENSE
Keywords: async,cidr,dns,network,proxy,scanner,slipstream,terminal,textual,tui
Classifier: Development Status :: 4 - Beta
Classifier: Environment :: Console
Classifier: Intended Audience :: Developers
Classifier: Intended Audience :: System Administrators
Classifier: License :: OSI Approved :: MIT License
Classifier: Operating System :: OS Independent
Classifier: Programming Language :: Python :: 3
Classifier: Programming Language :: Python :: 3.11
Classifier: Programming Language :: Python :: 3.12
Classifier: Programming Language :: Python :: 3.13
Classifier: Topic :: Internet :: Name Service (DNS)
Classifier: Topic :: System :: Networking
Classifier: Topic :: Utilities
Requires-Python: >=3.11
Requires-Dist: aiodns>=3.1.0
Requires-Dist: httpx[socks]>=0.25.0
Requires-Dist: loguru>=0.7.0
Requires-Dist: orjson>=3.9.0
Requires-Dist: pycares>=4.3.0
Requires-Dist: pyperclip>=1.8.0
Requires-Dist: textual>=0.47.0
